{
  "project_info": {
    "project_number": "68614643701",
    "project_id": "retorki-feladatkezelo-02",
    "storage_bucket": "retorki-feladatkezelo-02.firebasestorage.app"
  },
  "client": [
    {
      "client_info": {
        "mobilesdk_app_id": "1:68614643701:android:2a5bf2cfbdd486a3124abc",
        "android_client_info": {
          "package_name": "com.example.retorki_feladatkezelo_02"
        }
      },
      "oauth_client": [],
      "api_key": [
        {
          "current_key": "AIzaSyCFhCPIlodUC8cGdJK4ZWK81tGyJqhxiXA"
        }
      ],
      "services": {
        "appinvite_service": {
          "other_platform_oauth_client": []
        }
      }
    }
  ],
  "configuration_version": "1"
}